MANIFEST.in
changelog.rst
credits.txt
readme.rst
setup.py
SQLAlchemyBWC.egg-info/PKG-INFO
SQLAlchemyBWC.egg-info/SOURCES.txt
SQLAlchemyBWC.egg-info/dependency_links.txt
SQLAlchemyBWC.egg-info/not-zip-safe
SQLAlchemyBWC.egg-info/requires.txt
SQLAlchemyBWC.egg-info/top_level.txt
docs/coverage.txt
sqlalchemybwc/__init__.py
sqlalchemybwc/__init__.py~
sqlalchemybwc/events.py
sqlalchemybwc/events.py~
sqlalchemybwc/version.txt
sqlalchemybwc/config/__init__.py
sqlalchemybwc/config/settings.py
sqlalchemybwc/config/settings.py~
sqlalchemybwc/lib/__init__.py
sqlalchemybwc/lib/columns.py
sqlalchemybwc/lib/columns.py~
sqlalchemybwc/lib/declarative.py
sqlalchemybwc/lib/declarative.py~
sqlalchemybwc/lib/decorators.py
sqlalchemybwc/lib/decorators.py~
sqlalchemybwc/lib/helpers.py
sqlalchemybwc/lib/helpers.py~
sqlalchemybwc/lib/middleware.py
sqlalchemybwc/lib/middleware.py~
sqlalchemybwc/lib/sql.py
sqlalchemybwc/lib/sql.py~
sqlalchemybwc/lib/sqlitefktg4sa.py
sqlalchemybwc/lib/sqlitefktg4sa.py~
sqlalchemybwc/lib/testing.py
sqlalchemybwc/lib/validators.py
sqlalchemybwc/lib/validators.py~
sqlalchemybwc/tasks/__init__.py
sqlalchemybwc/tasks/clear_db.py
sqlalchemybwc/tasks/clear_db.py~
sqlalchemybwc/tasks/clear_db_data.py
sqlalchemybwc/tasks/clear_db_data.py~
sqlalchemybwc/tasks/init_db.py
sqlalchemybwc/tasks/init_db.py~
sqlalchemybwc_ta/__init__.py
sqlalchemybwc_ta/application.py
sqlalchemybwc_ta/application.py~
sqlalchemybwc_ta/test_beaker.db
sqlalchemybwc_ta/views.py
sqlalchemybwc_ta/views.py~
sqlalchemybwc_ta/components/__init__.py
sqlalchemybwc_ta/components/foo/__init__.py
sqlalchemybwc_ta/components/foo/sql/run_sql_test1.sql
sqlalchemybwc_ta/components/foo/sql/run_dir_test/00_test1.sql
sqlalchemybwc_ta/components/foo/sql/run_dir_test/01_test1.sql
sqlalchemybwc_ta/components/foo/sql/run_dir_test/02_sqlite.sql
sqlalchemybwc_ta/config/__init__.py
sqlalchemybwc_ta/config/appveyor_mssql.tpl
sqlalchemybwc_ta/config/appveyor_postgres.tpl
sqlalchemybwc_ta/config/circle_postgres.tpl
sqlalchemybwc_ta/config/settings.py
sqlalchemybwc_ta/config/settings.py~
sqlalchemybwc_ta/config/site_settings.py_tpl
sqlalchemybwc_ta/model/__init__.py
sqlalchemybwc_ta/model/entities.py
sqlalchemybwc_ta/model/entities.py~
