Metadata-Version: 1.1
Name: SQLAlchemyBWC
Version: 0.3.0
Summary: An SQLAlchemy component for BlazeWeb applications
Home-page: https://github.com/blazelibs/sqlalchemybwc/
Author: Randy Syring
Author-email: randy.syring@level12.io
License: BSD
Platform: UNKNOWN
Classifier: Development Status :: 4 - Beta
Classifier: Intended Audience :: Developers
Classifier: Programming Language :: Python :: 2.7
Classifier: Programming Language :: Python :: 3.4
Classifier: Programming Language :: Python :: 3.5
Classifier: License :: OSI Approved :: BSD License
